Metadata-Version: 2.1
Name: aldian-probability
Version: 0.1
Summary: Gaussian and Binomial distributions
Home-page: UNKNOWN
Author: Aldian Fazrihady
Author-email: mobile@aldian.net
License: UNKNOWN
Platform: UNKNOWN
